setup.py
pika_simple_daemon/__init__.py
pika_simple_daemon/queue.py
pika_simple_daemon/tests.py
pika_simple_daemon.egg-info/PKG-INFO
pika_simple_daemon.egg-info/SOURCES.txt
pika_simple_daemon.egg-info/dependency_links.txt
pika_simple_daemon.egg-info/not-zip-safe
pika_simple_daemon.egg-info/requires.txt
pika_simple_daemon.egg-info/top_level.txt