Metadata-Version: 1.0
Name: pika-simple-daemon
Version: 0.1.7
Summary: Simple Pika Daemon
Home-page: https://github.com/Tilley/pika_simple_daemon
Author: dtilleyshort
Author-email: david.tilleyshort@gmail.com
License: BSD
Platform: linux
Classifier: Development Status :: 2 - Pre-Alpha
Classifier: Operating System :: POSIX :: Linux
Classifier: Programming Language :: Python
